bosdyn/__init__.py
bosdyn/deprecated.py
bosdyn/geometry.py
bosdyn/util.py
bosdyn/bddf/__init__.py
bosdyn/bddf/base_data_reader.py
bosdyn/bddf/block_writer.py
bosdyn/bddf/bosdyn.py
bosdyn/bddf/common.py
bosdyn/bddf/data_reader.py
bosdyn/bddf/data_writer.py
bosdyn/bddf/file_indexer.py
bosdyn/bddf/grpc_proto_reader.py
bosdyn/bddf/grpc_reader.py
bosdyn/bddf/grpc_service_reader.py
bosdyn/bddf/grpc_service_writer.py
bosdyn/bddf/message_reader.py
bosdyn/bddf/pod_series_reader.py
bosdyn/bddf/pod_series_writer.py
bosdyn/bddf/protobuf_channel_reader.py
bosdyn/bddf/protobuf_reader.py
bosdyn/bddf/protobuf_series_writer.py
bosdyn/bddf/stream_data_reader.py
bosdyn_core-4.1.0.dist-info/METADATA
bosdyn_core-4.1.0.dist-info/WHEEL
bosdyn_core-4.1.0.dist-info/top_level.txt
bosdyn_core-4.1.0.dist-info/RECORD
