Metadata-Version: 2.1
Name: bosdyn-core
Version: 4.1.0
Summary: Boston Dynamics API Core code and interfaces
Home-page: https://dev.bostondynamics.com/
Author: Boston Dynamics
Author-email: support@bostondynamics.com
Project-URL: Documentation, https://dev.bostondynamics.com/
Project-URL: Source, https://github.com/boston-dynamics/spot-sdk/
Classifier: Programming Language :: Python :: 3.7
Classifier: Programming Language :: Python :: 3.8
Classifier: Programming Language :: Python :: 3.9
Classifier: Programming Language :: Python :: 3.10
Classifier: License :: Other/Proprietary License
Classifier: Operating System :: OS Independent
Requires-Python: >=3.6
Requires-Dist: bosdyn-api (==4.1.0)
Requires-Dist: Deprecated (~=1.2.10)
